syncnote/__init__.py
syncnote/get_version.py
syncnote/mynote.py
syncnote/sync.py
syncnote/version.py
syncnote-0.1.0.3.dist-info/LICENSE
syncnote-0.1.0.3.dist-info/METADATA
syncnote-0.1.0.3.dist-info/WHEEL
syncnote-0.1.0.3.dist-info/top_level.txt
syncnote-0.1.0.3.dist-info/RECORD
