Metadata-Version: 2.1
Name: syncnote
Version: 0.1.0.3
Summary: None
Home-page: https://github.com/beidongjiedeguang/SyncNote
Author: K.y
Author-email: beidongjiedeguang@gmail.com
License: MIT
Keywords: Deep Learning,Machine Learning,Neural Networks,Natural Language Processing,Computer Vision
Platform: UNKNOWN
Classifier: Operating System :: OS Independent
Classifier: Intended Audience :: Developers
Classifier: Intended Audience :: Science/Research
Classifier: Topic :: Scientific/Engineering :: Artificial Intelligence
Classifier: Programming Language :: Python :: 3
Classifier: Programming Language :: Python :: 3.5
Classifier: Programming Language :: Python :: 3.6
Classifier: Programming Language :: Python :: 3.7
Classifier: Programming Language :: Python :: 3.8
Requires-Dist: guang
Requires-Dist: psutil
Requires-Dist: pretty-errors
Requires-Dist: ephem
Requires-Dist: dill
Requires-Dist: pyprobar
Requires-Dist: paramiko
